slate_utils/__init__.py
slate_utils/assign.py
slate_utils/consolidate.py
slate_utils/impersonate.py
slate_utils/imports.py
slate_utils/query.py
slate_utils/rules.py
slate_utils/session.py
slate_utils/wait.py
slate_utils/common/__init__.py
slate_utils/common/exceptions.py
slate_utils/common/html.py
slate_utils/common/patterns.py
slate_utils/common/pkv.py
slate_utils/consolidated_records/__init__.py
slate_utils/consolidated_records/consolidators.py
slate_utils/docs/__init__.py
slate_utils/docs/base.py
slate_utils/docs/query.py
slate_utils/docs/utils.py
tests/__init__.py
tests/test_session.py
tests/common/__init__.py
tests/common/test_html.py
tests/common/test_pkv.py
slate_utils-0.0.5.6.dist-info/METADATA
slate_utils-0.0.5.6.dist-info/WHEEL
slate_utils-0.0.5.6.dist-info/top_level.txt
slate_utils-0.0.5.6.dist-info/RECORD
