Metadata-Version: 2.1
Name: slate-utils
Version: 0.0.5.6
Summary: Some simple utilites to help automate tasks in Slate.
Home-page: UNKNOWN
Author: Jamie Davis
Author-email: jamjam@umich.edu
License: BSD
Platform: UNKNOWN
Requires-Dist: beautifulsoup4
Requires-Dist: loguru
Requires-Dist: lxml
Requires-Dist: requests
Requires-Dist: selenium
Requires-Dist: umdriver
